compas_pb/__init__.py
compas_pb/api.py
compas_pb/conversions.py
compas_pb/core.py
compas_pb/invocations.py
compas_pb/plugin.py
compas_pb/registry.py
compas_pb/generated/arc_pb2.py
compas_pb/generated/bezier_pb2.py
compas_pb/generated/box_pb2.py
compas_pb/generated/capsule_pb2.py
compas_pb/generated/circle_pb2.py
compas_pb/generated/cone_pb2.py
compas_pb/generated/cylinder_pb2.py
compas_pb/generated/ellipse_pb2.py
compas_pb/generated/frame_pb2.py
compas_pb/generated/hyperbola_pb2.py
compas_pb/generated/line_pb2.py
compas_pb/generated/mesh_pb2.py
compas_pb/generated/message_pb2.py
compas_pb/generated/parabola_pb2.py
compas_pb/generated/plane_pb2.py
compas_pb/generated/point_pb2.py
compas_pb/generated/pointcloud_pb2.py
compas_pb/generated/polygon_pb2.py
compas_pb/generated/polyhedron_pb2.py
compas_pb/generated/polyline_pb2.py
compas_pb/generated/projection_pb2.py
compas_pb/generated/quaternion_pb2.py
compas_pb/generated/reflection_pb2.py
compas_pb/generated/rotation_pb2.py
compas_pb/generated/scale_pb2.py
compas_pb/generated/shear_pb2.py
compas_pb/generated/sphere_pb2.py
compas_pb/generated/torus_pb2.py
compas_pb/generated/transformation_pb2.py
compas_pb/generated/translation_pb2.py
compas_pb/generated/vector_pb2.py
compas_pb/protobuf_defs/compas_pb/generated/arc.proto
compas_pb/protobuf_defs/compas_pb/generated/bezier.proto
compas_pb/protobuf_defs/compas_pb/generated/box.proto
compas_pb/protobuf_defs/compas_pb/generated/capsule.proto
compas_pb/protobuf_defs/compas_pb/generated/circle.proto
compas_pb/protobuf_defs/compas_pb/generated/cone.proto
compas_pb/protobuf_defs/compas_pb/generated/cylinder.proto
compas_pb/protobuf_defs/compas_pb/generated/ellipse.proto
compas_pb/protobuf_defs/compas_pb/generated/frame.proto
compas_pb/protobuf_defs/compas_pb/generated/hyperbola.proto
compas_pb/protobuf_defs/compas_pb/generated/line.proto
compas_pb/protobuf_defs/compas_pb/generated/mesh.proto
compas_pb/protobuf_defs/compas_pb/generated/message.proto
compas_pb-0.4.8.dist-info/licenses/LICENSE
compas_pb-0.4.8.dist-info/METADATA
compas_pb-0.4.8.dist-info/WHEEL
compas_pb-0.4.8.dist-info/top_level.txt
compas_pb-0.4.8.dist-info/RECORD
