Metadata-Version: 2.4
Name: compas_pb
Version: 0.4.8
Summary: Protobuf extension for COMPAS Data
Author-email: Wei-Ting Chen <chenwei@arch.ethz.ch>, Chen Kasirer <kasirer@arch.ethz.ch>
License: MIT License
Project-URL: Homepage, https://gramaziokohler.github.io/compas_pb
Project-URL: Documentation, https://gramaziokohler.github.io/compas_pb
Project-URL: Repository, https://github.com/gramaziokohler/compas_pb
Project-URL: Changelog, https://github.com/gramaziokohler/compas_pb/blob/main/CHANGELOG.md
Project-URL: Issues, https://github.com/gramaziokohler/compas_pb/issues
Project-URL: Forum, https://forum.compas-framework.org/
Classifier: Development Status :: 4 - Beta
Classifier: Topic :: Scientific/Engineering
Classifier: Operating System :: Unix
Classifier: Operating System :: POSIX
Classifier: Operating System :: Microsoft :: Windows
Classifier: Programming Language :: Python
Classifier: Programming Language :: Python :: 3
Classifier: Programming Language :: Python :: 3.10
Classifier: Programming Language :: Python :: 3.11
Classifier: Programming Language :: Python :: 3.12
Requires-Python: >=3.9
License-File: LICENSE
Requires-Dist: compas>=2
Requires-Dist: protobuf>=6.31.1
Requires-Dist: importlib-metadata>=5; python_version == "3.9"
Provides-Extra: dev
Requires-Dist: attrs>=17.4; extra == "dev"
Requires-Dist: bump-my-version; extra == "dev"
Requires-Dist: compas_invocations2; extra == "dev"
Requires-Dist: invoke>=0.14; extra == "dev"
Requires-Dist: ruff; extra == "dev"
Requires-Dist: sphinx_compas2_theme; extra == "dev"
Requires-Dist: twine; extra == "dev"
Requires-Dist: wheel; extra == "dev"
Requires-Dist: pytest-mock; extra == "dev"
Requires-Dist: build; extra == "dev"
Provides-Extra: docs
Requires-Dist: markdown-callouts>=0.4; extra == "docs"
Requires-Dist: markdown-exec>=1.8; extra == "docs"
Requires-Dist: mike; extra == "docs"
Requires-Dist: mkdocs>=1.6; extra == "docs"
Requires-Dist: mkdocs-autorefs>=1.4; extra == "docs"
Requires-Dist: mkdocs-coverage>=1.0; extra == "docs"
Requires-Dist: mkdocs-git-revision-date-localized-plugin>=1.2; extra == "docs"
Requires-Dist: mkdocs-llmstxt>=0.2; extra == "docs"
Requires-Dist: mkdocs-material>=9.5; extra == "docs"
Requires-Dist: mkdocs-minify-plugin>=0.8; extra == "docs"
Requires-Dist: mkdocs-redirects>=1.2; extra == "docs"
Requires-Dist: mkdocs-section-index>=0.3; extra == "docs"
Requires-Dist: mkdocstrings[python]; extra == "docs"
Requires-Dist: pydantic>=2.10; extra == "docs"
Requires-Dist: tomli>=2.0; python_version < "3.11" and extra == "docs"
Dynamic: license-file
